cbdevtools/LICENSE.txt
cbdevtools/README.md
cbdevtools/__init__.py
cbdevtools/addfindsrc.py
cbdevtools/easysign.py
cbdevtools/orpystedata.py
cbdevtools/shortdir.py
cbdevtools-0.0.11b0.dist-info/WHEEL
cbdevtools-0.0.11b0.dist-info/METADATA
cbdevtools-0.0.11b0.dist-info/RECORD
