Metadata-Version: 2.1
Name: cbdevtools
Version: 0.0.11b0
Summary: "Common Box of Dev Tools" proposing small scripts that can be helpful.
Home-page: https://github.com/projetmbc/tools-for-dev/tree/master/cbdevtools
License: GNU License Version 3
Author: Christophe BAL
Maintainer: Christophe BAL
Requires-Python: >=3.8,<4.0
Classifier: License :: Other/Proprietary License
Classifier: Programming Language :: Python :: 3
Classifier: Programming Language :: Python :: 3.8
Classifier: Programming Language :: Python :: 3.9
Requires-Dist: orpyste (>=1.3.2-beta.0,<2.0.0)
Requires-Dist: pytest (>=6.2.4,<7.0.0)
Project-URL: Repository, https://github.com/projetmbc/tools-for-dev/tree/master/cbdevtools
